Workbook

Sheet README
A1: TCL Tech Solutions — Component Upgrade Membership Model
A2: Subscription-based annual upgrade program | Prepared for Damon Jackson, CEO | Brainstorm working model
A5: PURPOSE
B6: A financial model to stress-test a recurring monthly membership that lets clients accrue credit toward annual
B7: component upgrades — analogous to AT&T's device upgrade program, adapted to custom home-automation hardware.
A9: THE GOVERNING RULE
B10: Credit granted is a discount off MSRP. Customer out-of-pocket = MSRP - Credit.
B11: To never sell below cost: Maximum Credit = MSRP - Dealer Cost = the SPREAD.
B12: The program only works on HIGH-SPREAD inventory (50-point gear). It is a spread-harvesting engine, not a discount.
A14: HOW TO USE
B15: 1. Assumptions — set the membership tiers, bonus %, and rollover rules (blue cells = your inputs).
B16: 2. SKU Catalog — enter each component's dealer cost and MSRP; the sheet computes spread and the safe credit cap.
B17: 3. Tier Economics — pick a tier; see customer cost vs. TCL profit for every SKU, with a viability flag.
B18: 4. Rollover Schedule — shows year-over-year credit accrual and the anti-banking cap.
B19: 5. Portfolio Model — scales it: customer base x upgrade frequency = recurring revenue and net profit.
A21: COLOR KEY
B22: Blue text = input you can change. Black text = formula. Green text = pulled from another sheet.
B23: Yellow fill = key assumption to review.
A25: NOTE ON CUSTOMER VALUE
B26: Netted against subscription paid, real dollar savings are modest. The product sells CADENCE & CONVENIENCE —
B27: always-current technology with no $3,000-$4,000 lump sum. Anchor all marketing to MSRP and membership perks.

Sheet Assumptions
A1: Assumptions & Drivers
A2: Blue cells are inputs. Adjust here and the whole model updates.
A4: Program-Wide Drivers
A5: Driver | B5: Value | C5: Notes
A6: Credit bonus over subscription paid | B6: 0.25 | C6: Year-1 credit = annual subscription x (1 + this). Damon's target: $480 paid -> $600 credit.
A7: Annual rollover bonus (if unused) | B7: 300 | C7: Added each year credit goes unredeemed, to show ongoing value.
A8: Rollover cap (x year-1 credit) | B8: 2 | C8: Max accruable credit, to prevent customers banking for a margin-killing redemption.
A9: Recommended credit as % of spread | B9: 0.75 | C9: Safety governor: keep credit below the full spread to retain hardware margin.
A10: Programming labor rate ($/hour) | B10: 120 | C10: Used for the programming membership tier.
A12: Membership Tiers
A13: Tier | B13: Monthly ($) | C13: Annual Paid ($) | D13: Year-1 Credit ($) | E13: Effective Bonus | F13: Target Spread (min)
A14: Tier 1 - Standard | B14: 40 | C14: =B14*12 -> 480 | D14: =C14*(1+$B$6) -> 600 | E14: =D14/C14-1 -> 0.25 | F14: =D14/$B$9 -> 800
A15: Tier 2 - Plus | B15: 75 | C15: =B15*12 -> 900 | D15: =C15*(1+$B$6) -> 1125 | E15: =D15/C15-1 -> 0.25 | F15: =D15/$B$9 -> 1500
A16: Tier 3 - Premium | B16: 100 | C16: =B16*12 -> 1200 | D16: =C16*(1+$B$6) -> 1500 | E16: =D16/C16-1 -> 0.25 | F16: =D16/$B$9 -> 2000
A17: Programming | B17: 25 | C17: =B17*12 -> 300 | D17: =C17*(1+$B$6) -> 375 | E17: =D17/C17-1 -> 0.25 | F17: =D17/$B$9 -> 500
A19: Programming tier delivers labor, not hardware: $25/mo = $300/yr collected -> 2 hrs free programming ($240 value at $120/hr).

Sheet SKU Catalog
A1: SKU Catalog — Spread Analysis
A2: Enter dealer cost and MSRP (blue). Spread, margin, and the safe credit cap calculate automatically.
A4: Components (18-item inventory)
A5: Component | B5: Dealer Cost ($) | C5: MSRP ($) | D5: Spread ($) | E5: Spread (points %) | F5: Max Credit = Spread ($) | G5: Recommended Credit ($) | H5: Program Fit | I5: Basis
A6: URC cinema remote | B6: 650 | C6: 1300 | D6: =IF(C6="","",C6-B6) -> 650 | E6: =IF(C6="","",D6/C6) -> 0.5 | F6: =IF(C6="","",D6) -> 650 | G6: =IF(C6="","",D6*Assumptions!$B$9) -> 487.5 | H6: =IF(C6="","",IF(E6>=0.5,"STRONG",IF(E6>=0.35,"MARGINAL","POOR"))) -> STRONG | I6: Actual
A7: Bookshelf speakers (pair) | B7: 250 | C7: 899 | D7: =IF(C7="","",C7-B7) -> 649 | E7: =IF(C7="","",D7/C7) -> 0.72191324 | F7: =IF(C7="","",D7) -> 649 | G7: =IF(C7="","",D7*Assumptions!$B$9) -> 486.75 | H7: =IF(C7="","",IF(E7>=0.5,"STRONG",IF(E7>=0.35,"MARGINAL","POOR"))) -> STRONG | I7: Actual
A8: Marantz pre-amp | B8: 2800 | C8: 4000 | D8: =IF(C8="","",C8-B8) -> 1200 | E8: =IF(C8="","",D8/C8) -> 0.3 | F8: =IF(C8="","",D8) -> 1200 | G8: =IF(C8="","",D8*Assumptions!$B$9) -> 900 | H8: =IF(C8="","",IF(E8>=0.5,"STRONG",IF(E8>=0.35,"MARGINAL","POOR"))) -> POOR | I8: Actual
A9: Denon AV receiver | B9: 1200 | C9: 2000 | D9: =IF(C9="","",C9-B9) -> 800 | E9: =IF(C9="","",D9/C9) -> 0.4 | F9: =IF(C9="","",D9) -> 800 | G9: =IF(C9="","",D9*Assumptions!$B$9) -> 600 | H9: =IF(C9="","",IF(E9>=0.5,"STRONG",IF(E9>=0.35,"MARGINAL","POOR"))) -> MARGINAL | I9: Estimate
A10: URC total-control processor | B10: 700 | C10: 1500 | D10: =IF(C10="","",C10-B10) -> 800 | E10: =IF(C10="","",D10/C10) -> 0.53333333 | F10: =IF(C10="","",D10) -> 800 | G10: =IF(C10="","",D10*Assumptions!$B$9) -> 600 | H10: =IF(C10="","",IF(E10>=0.5,"STRONG",IF(E10>=0.35,"MARGINAL","POOR"))) -> STRONG | I10: Estimate
A11: In-ceiling speakers (pair) | B11: 180 | C11: 600 | D11: =IF(C11="","",C11-B11) -> 420 | E11: =IF(C11="","",D11/C11) -> 0.7 | F11: =IF(C11="","",D11) -> 420 | G11: =IF(C11="","",D11*Assumptions!$B$9) -> 315 | H11: =IF(C11="","",IF(E11>=0.5,"STRONG",IF(E11>=0.35,"MARGINAL","POOR"))) -> STRONG | I11: Estimate
A12: Outdoor speakers (pair) | B12: 220 | C12: 700 | D12: =IF(C12="","",C12-B12) -> 480 | E12: =IF(C12="","",D12/C12) -> 0.68571429 | F12: =IF(C12="","",D12) -> 480 | G12: =IF(C12="","",D12*Assumptions!$B$9) -> 360 | H12: =IF(C12="","",IF(E12>=0.5,"STRONG",IF(E12>=0.35,"MARGINAL","POOR"))) -> STRONG | I12: Estimate
A13: Powered subwoofer | B13: 450 | C13: 1100 | D13: =IF(C13="","",C13-B13) -> 650 | E13: =IF(C13="","",D13/C13) -> 0.59090909 | F13: =IF(C13="","",D13) -> 650 | G13: =IF(C13="","",D13*Assumptions!$B$9) -> 487.5 | H13: =IF(C13="","",IF(E13>=0.5,"STRONG",IF(E13>=0.35,"MARGINAL","POOR"))) -> STRONG | I13: Estimate
A14: 4K home-theater projector | B14: 2500 | C14: 5000 | D14: =IF(C14="","",C14-B14) -> 2500 | E14: =IF(C14="","",D14/C14) -> 0.5 | F14: =IF(C14="","",D14) -> 2500 | G14: =IF(C14="","",D14*Assumptions!$B$9) -> 1875 | H14: =IF(C14="","",IF(E14>=0.5,"STRONG",IF(E14>=0.35,"MARGINAL","POOR"))) -> STRONG | I14: Estimate
A15: Motorized projector screen | B15: 900 | C15: 2200 | D15: =IF(C15="","",C15-B15) -> 1300 | E15: =IF(C15="","",D15/C15) -> 0.59090909 | F15: =IF(C15="","",D15) -> 1300 | G15: =IF(C15="","",D15*Assumptions!$B$9) -> 975 | H15: =IF(C15="","",IF(E15>=0.5,"STRONG",IF(E15>=0.35,"MARGINAL","POOR"))) -> STRONG | I15: Estimate
A16: Multi-zone amplifier (8-ch) | B16: 800 | C16: 1800 | D16: =IF(C16="","",C16-B16) -> 1000 | E16: =IF(C16="","",D16/C16) -> 0.55555556 | F16: =IF(C16="","",D16) -> 1000 | G16: =IF(C16="","",D16*Assumptions!$B$9) -> 750 | H16: =IF(C16="","",IF(E16>=0.5,"STRONG",IF(E16>=0.35,"MARGINAL","POOR"))) -> STRONG | I16: Estimate
A17: Network video recorder (NVR) | B17: 500 | C17: 1200 | D17: =IF(C17="","",C17-B17) -> 700 | E17: =IF(C17="","",D17/C17) -> 0.58333333 | F17: =IF(C17="","",D17) -> 700 | G17: =IF(C17="","",D17*Assumptions!$B$9) -> 525 | H17: =IF(C17="","",IF(E17>=0.5,"STRONG",IF(E17>=0.35,"MARGINAL","POOR"))) -> STRONG | I17: Estimate
... A23: Touchscreen wall controller 10" | B23: 600 | C23: 1400 | D23: =IF(C23="","",C23-B23) -> 800 | E23: =IF(C23="","",D23/C23) -> 0.57142857 | F23: =IF(C23="","",D23) -> 800 | G23: =IF(C23="","",D23*Assumptions!$B$9) -> 600 | H23: =IF(C23="","",IF(E23>=0.5,"STRONG",IF(E23>=0.35,"MARGINAL","POOR"))) -> STRONG | I23: Estimate
A25: Rule of thumb: STRONG = 50+ points of spread (ideal program inventory). POOR = thin margin; a full credit drives hardware profit to zero.
A26: Rows marked 'Estimate' use placeholder pricing - overwrite the blue Dealer Cost and MSRP cells with TCL's actual dealer pricing.

Sheet Tier Economics
A1: Tier Economics — Customer vs. TCL
A2: Choose a tier; see what the customer pays and what TCL earns on each component in year one.
A4: Select Membership Tier
A5: Tier: | B5: Tier 1 - Standard | D5: Monthly: | E5: =VLOOKUP($B$5,Assumptions!$A$14:$D$17,2,FALSE()) -> 40 | F5: Annual paid: | G5: =VLOOKUP($B$5,Assumptions!$A$14:$D$17,3,FALSE()) -> 480 | H5: Yr-1 credit: | I5: =VLOOKUP($B$5,Assumptions!$A$14:$D$17,4,FALSE()) -> 600
A7: Year-One Economics by Component
A8: Component | B8: MSRP | C8: Dealer Cost | D8: Credit Applied | E8: Customer Out-of-Pocket | F8: Customer Total (sub+OOP) | G8: Savings vs MSRP | H8: TCL Profit (sub+margin) | I8: Viable?
A9: =IF('SKU Catalog'!A6="","",'SKU Catalog'!A6) -> URC cinema remote | B9: =IF('SKU Catalog'!C6="","",'SKU Catalog'!C6) -> 1300 | C9: =IF('SKU Catalog'!C6="","",'SKU Catalog'!B6) -> 650 | D9: =IF(B9="","",MIN($I$5,'SKU Catalog'!D6)) -> 600 | E9: =IF(B9="","",B9-D9) -> 700 | F9: =IF(B9="","",$G$5+E9) -> 1180 | G9: =IF(B9="","",B9-F9) -> 120 | H9: =IF(B9="","",$G$5+(E9-C9)) -> 530 | I9: =IF(B9="","",IF(AND(E9>=C9,G9>0),"YES","CHECK")) -> YES
A10: =IF('SKU Catalog'!A7="","",'SKU Catalog'!A7) -> Bookshelf speakers (pair) | B10: =IF('SKU Catalog'!C7="","",'SKU Catalog'!C7) -> 899 | C10: =IF('SKU Catalog'!C7="","",'SKU Catalog'!B7) -> 250 | D10: =IF(B10="","",MIN($I$5,'SKU Catalog'!D7)) -> 600 | E10: =IF(B10="","",B10-D10) -> 299 | F10: =IF(B10="","",$G$5+E10) -> 779 | G10: =IF(B10="","",B10-F10) -> 120 | H10: =IF(B10="","",$G$5+(E10-C10)) -> 529 | I10: =IF(B10="","",IF(AND(E10>=C10,G10>0),"YES","CHECK")) -> YES
A11: =IF('SKU Catalog'!A8="","",'SKU Catalog'!A8) -> Marantz pre-amp | B11: =IF('SKU Catalog'!C8="","",'SKU Catalog'!C8) -> 4000 | C11: =IF('SKU Catalog'!C8="","",'SKU Catalog'!B8) -> 2800 | D11: =IF(B11="","",MIN($I$5,'SKU Catalog'!D8)) -> 600 | E11: =IF(B11="","",B11-D11) -> 3400 | F11: =IF(B11="","",$G$5+E11) -> 3880 | G11: =IF(B11="","",B11-F11) -> 120 | H11: =IF(B11="","",$G$5+(E11-C11)) -> 1080 | I11: =IF(B11="","",IF(AND(E11>=C11,G11>0),"YES","CHECK")) -> YES
A12: =IF('SKU Catalog'!A9="","",'SKU Catalog'!A9) -> Denon AV receiver | B12: =IF('SKU Catalog'!C9="","",'SKU Catalog'!C9) -> 2000 | C12: =IF('SKU Catalog'!C9="","",'SKU Catalog'!B9) -> 1200 | D12: =IF(B12="","",MIN($I$5,'SKU Catalog'!D9)) -> 600 | E12: =IF(B12="","",B12-D12) -> 1400 | F12: =IF(B12="","",$G$5+E12) -> 1880 | G12: =IF(B12="","",B12-F12) -> 120 | H12: =IF(B12="","",$G$5+(E12-C12)) -> 680 | I12: =IF(B12="","",IF(AND(E12>=C12,G12>0),"YES","CHECK")) -> YES
A13: =IF('SKU Catalog'!A10="","",'SKU Catalog'!A10) -> URC total-control processor | B13: =IF('SKU Catalog'!C10="","",'SKU Catalog'!C10) -> 1500 | C13: =IF('SKU Catalog'!C10="","",'SKU Catalog'!B10) -> 700 | D13: =IF(B13="","",MIN($I$5,'SKU Catalog'!D10)) -> 600 | E13: =IF(B13="","",B13-D13) -> 900 | F13: =IF(B13="","",$G$5+E13) -> 1380 | G13: =IF(B13="","",B13-F13) -> 120 | H13: =IF(B13="","",$G$5+(E13-C13)) -> 680 | I13: =IF(B13="","",IF(AND(E13>=C13,G13>0),"YES","CHECK")) -> YES
A14: =IF('SKU Catalog'!A11="","",'SKU Catalog'!A11) -> In-ceiling speakers (pair) | B14: =IF('SKU Catalog'!C11="","",'SKU Catalog'!C11) -> 600 | C14: =IF('SKU Catalog'!C11="","",'SKU Catalog'!B11) -> 180 | D14: =IF(B14="","",MIN($I$5,'SKU Catalog'!D11)) -> 420 | E14: =IF(B14="","",B14-D14) -> 180 | F14: =IF(B14="","",$G$5+E14) -> 660 | G14: =IF(B14="","",B14-F14) -> -60 | H14: =IF(B14="","",$G$5+(E14-C14)) -> 480 | I14: =IF(B14="","",IF(AND(E14>=C14,G14>0),"YES","CHECK")) -> CHECK
A15: =IF('SKU Catalog'!A12="","",'SKU Catalog'!A12) -> Outdoor speakers (pair) | B15: =IF('SKU Catalog'!C12="","",'SKU Catalog'!C12) -> 700 | C15: =IF('SKU Catalog'!C12="","",'SKU Catalog'!B12) -> 220 | D15: =IF(B15="","",MIN($I$5,'SKU Catalog'!D12)) -> 480 | E15: =IF(B15="","",B15-D15) -> 220 | F15: =IF(B15="","",$G$5+E15) -> 700 | G15: =IF(B15="","",B15-F15) -> 0 | H15: =IF(B15="","",$G$5+(E15-C15)) -> 480 | I15: =IF(B15="","",IF(AND(E15>=C15,G15>0),"YES","CHECK")) -> CHECK
A16: =IF('SKU Catalog'!A13="","",'SKU Catalog'!A13) -> Powered subwoofer | B16: =IF('SKU Catalog'!C13="","",'SKU Catalog'!C13) -> 1100 | C16: =IF('SKU Catalog'!C13="","",'SKU Catalog'!B13) -> 450 | D16: =IF(B16="","",MIN($I$5,'SKU Catalog'!D13)) -> 600 | E16: =IF(B16="","",B16-D16) -> 500 | F16: =IF(B16="","",$G$5+E16) -> 980 | G16: =IF(B16="","",B16-F16) -> 120 | H16: =IF(B16="","",$G$5+(E16-C16)) -> 530 | I16: =IF(B16="","",IF(AND(E16>=C16,G16>0),"YES","CHECK")) -> YES
A17: =IF('SKU Catalog'!A14="","",'SKU Catalog'!A14) -> 4K home-theater projector | B17: =IF('SKU Catalog'!C14="","",'SKU Catalog'!C14) -> 5000 | C17: =IF('SKU Catalog'!C14="","",'SKU Catalog'!B14) -> 2500 | D17: =IF(B17="","",MIN($I$5,'SKU Catalog'!D14)) -> 600 | E17: =IF(B17="","",B17-D17) -> 4400 | F17: =IF(B17="","",$G$5+E17) -> 4880 | G17: =IF(B17="","",B17-F17) -> 120 | H17: =IF(B17="","",$G$5+(E17-C17)) -> 2380 | I17: =IF(B17="","",IF(AND(E17>=C17,G17>0),"YES","CHECK")) -> YES
A18: =IF('SKU Catalog'!A15="","",'SKU Catalog'!A15) -> Motorized projector screen | B18: =IF('SKU Catalog'!C15="","",'SKU Catalog'!C15) -> 2200 | C18: =IF('SKU Catalog'!C15="","",'SKU Catalog'!B15) -> 900 | D18: =IF(B18="","",MIN($I$5,'SKU Catalog'!D15)) -> 600 | E18: =IF(B18="","",B18-D18) -> 1600 | F18: =IF(B18="","",$G$5+E18) -> 2080 | G18: =IF(B18="","",B18-F18) -> 120 | H18: =IF(B18="","",$G$5+(E18-C18)) -> 1180 | I18: =IF(B18="","",IF(AND(E18>=C18,G18>0),"YES","CHECK")) -> YES
A19: =IF('SKU Catalog'!A16="","",'SKU Catalog'!A16) -> Multi-zone amplifier (8-ch) | B19: =IF('SKU Catalog'!C16="","",'SKU Catalog'!C16) -> 1800 | C19: =IF('SKU Catalog'!C16="","",'SKU Catalog'!B16) -> 800 | D19: =IF(B19="","",MIN($I$5,'SKU Catalog'!D16)) -> 600 | E19: =IF(B19="","",B19-D19) -> 1200 | F19: =IF(B19="","",$G$5+E19) -> 1680 | G19: =IF(B19="","",B19-F19) -> 120 | H19: =IF(B19="","",$G$5+(E19-C19)) -> 880 | I19: =IF(B19="","",IF(AND(E19>=C19,G19>0),"YES","CHECK")) -> YES
A20: =IF('SKU Catalog'!A17="","",'SKU Catalog'!A17) -> Network video recorder (NVR) | B20: =IF('SKU Catalog'!C17="","",'SKU Catalog'!C17) -> 1200 | C20: =IF('SKU Catalog'!C17="","",'SKU Catalog'!B17) -> 500 | D20: =IF(B20="","",MIN($I$5,'SKU Catalog'!D17)) -> 600 | E20: =IF(B20="","",B20-D20) -> 600 | F20: =IF(B20="","",$G$5+E20) -> 1080 | G20: =IF(B20="","",B20-F20) -> 120 | H20: =IF(B20="","",$G$5+(E20-C20)) -> 580 | I20: =IF(B20="","",IF(AND(E20>=C20,G20>0),"YES","CHECK")) -> YES
... A26: =IF('SKU Catalog'!A23="","",'SKU Catalog'!A23) -> Touchscreen wall controller 10" | B26: =IF('SKU Catalog'!C23="","",'SKU Catalog'!C23) -> 1400 | C26: =IF('SKU Catalog'!C23="","",'SKU Catalog'!B23) -> 600 | D26: =IF(B26="","",MIN($I$5,'SKU Catalog'!D23)) -> 600 | E26: =IF(B26="","",B26-D26) -> 800 | F26: =IF(B26="","",$G$5+E26) -> 1280 | G26: =IF(B26="","",B26-F26) -> 120 | H26: =IF(B26="","",$G$5+(E26-C26)) -> 680 | I26: =IF(B26="","",IF(AND(E26>=C26,G26>0),"YES","CHECK")) -> YES
A28: Credit Applied is automatically capped at the component's spread so TCL never sells below dealer cost. 'CHECK' flags a money-losing or no-value redemption.
A29: Reality check: 'Savings vs MSRP' nets out subscription paid. Modest dollar savings is expected — the value sold is upgrade cadence and convenience.

Sheet Rollover Schedule
A1: Rollover Schedule — Anti-Banking Mechanic
A2: If a member does not redeem, credit grows at the rollover bonus, capped to protect margin.
A4: Select Tier
A5: Tier: | B5: Tier 1 - Standard | D5: Yr-1 credit: | E5: =VLOOKUP($B$5,Assumptions!$A$14:$D$17,4,FALSE()) -> 600 | F5: Annual paid: | G5: =VLOOKUP($B$5,Assumptions!$A$14:$D$17,3,FALSE()) -> 480
A7: 5-Year Credit Accrual (if never redeemed)
A8: Year | B8: Cumulative Subscription Paid | C8: Raw Accrued (uncapped) | D8: Rollover Cap | E8: Available Credit (capped) | F8: Credit as % of Paid | G8: Member-Visible Value
A9: Year 1 | B9: =$G$5*1 -> 480 | C9: =$E$5 -> 600 | D9: =$E$5*Assumptions!$B$8 -> 1200 | E9: =MIN(C9,D9) -> 600 | F9: =E9/B9 -> 1.25 | G9: =IF(C9>D9,"Capped","Growing") -> Growing
A10: Year 2 | B10: =$G$5*2 -> 960 | C10: =C9+Assumptions!$B$7 -> 900 | D10: =$E$5*Assumptions!$B$8 -> 1200 | E10: =MIN(C10,D10) -> 900 | F10: =E10/B10 -> 0.9375 | G10: =IF(C10>D10,"Capped","Growing") -> Growing
A11: Year 3 | B11: =$G$5*3 -> 1440 | C11: =C10+Assumptions!$B$7 -> 1200 | D11: =$E$5*Assumptions!$B$8 -> 1200 | E11: =MIN(C11,D11) -> 1200 | F11: =E11/B11 -> 0.83333333 | G11: =IF(C11>D11,"Capped","Growing") -> Growing
A12: Year 4 | B12: =$G$5*4 -> 1920 | C12: =C11+Assumptions!$B$7 -> 1500 | D12: =$E$5*Assumptions!$B$8 -> 1200 | E12: =MIN(C12,D12) -> 1200 | F12: =E12/B12 -> 0.625 | G12: =IF(C12>D12,"Capped","Growing") -> Capped
A13: Year 5 | B13: =$G$5*5 -> 2400 | C13: =C12+Assumptions!$B$7 -> 1800 | D13: =$E$5*Assumptions!$B$8 -> 1200 | E13: =MIN(C13,D13) -> 1200 | F13: =E13/B13 -> 0.5 | G13: =IF(C13>D13,"Capped","Growing") -> Capped
A15: The cap is the key defense: a member cannot bank indefinitely and then extract TCL's entire spread on one premium redemption.

Sheet Portfolio Model
A1: Portfolio Model — Scale Economics
A2: The real engine: a large base x low redemption frequency. Blue cells are inputs.
A4: Base Assumptions
A5: Total members enrolled | E5: 100
A6: Avg monthly fee (blended) ($) | E6: 50
A7: Avg upgrade frequency (every N years) | E7: 3
A8: Avg credit redeemed per upgrade ($) | E8: 600
A9: Avg hardware margin retained per upgrade ($) | E9: 75
A10: Avg servicing cost per member / year ($) | E10: 60
A12: Annual Results
A13: Metric | E13: Value | F13: Basis
A14: Recurring subscription revenue / year | E14: =$E$5*$E$6*12 -> 60000 | F14: Members x monthly x 12. The recurring float.
A15: Upgrades redeemed / year | E15: =$E$5/$E$7 -> 33.333333 | F15: Members divided by upgrade frequency.
A16: Hardware margin from upgrades / year | E16: =($E$5/$E$7)*$E$9 -> 2500 | F16: Redemptions x retained hardware margin.
A17: Servicing cost / year | E17: =$E$5*$E$10 -> 6000 | F17: Members x servicing cost.
A18: NET ANNUAL PROFIT | E18: =$E$5*$E$6*12+($E$5/$E$7)*$E$9-$E$5*$E$10 -> 56500 | F18: Subscription + hardware margin - servicing.
A19: Net profit per member / year | E19: =$E$18/$E$5 -> 565 | F19: Net annual profit / members.
A20: Effective program margin | E20: =$E$18/($E$5*$E$6*12) -> 0.94166667 | F20: Net profit / subscription revenue.
A22: Sensitivity — Net Profit vs. Upgrade Frequency
A23: Upgrade every (yrs) | B23: Net Annual Profit | C23: Per Member
A24: 1 | B24: =$E$5*$E$6*12+($E$5/A24)*$E$9-$E$5*$E$10 -> 61500 | C24: =B24/$E$5 -> 615
A25: 2 | B25: =$E$5*$E$6*12+($E$5/A25)*$E$9-$E$5*$E$10 -> 57750 | C25: =B25/$E$5 -> 577.5
A26: 3 | B26: =$E$5*$E$6*12+($E$5/A26)*$E$9-$E$5*$E$10 -> 56500 | C26: =B26/$E$5 -> 565
A27: 4 | B27: =$E$5*$E$6*12+($E$5/A27)*$E$9-$E$5*$E$10 -> 55875 | C27: =B27/$E$5 -> 558.75
A28: 5 | B28: =$E$5*$E$6*12+($E$5/A28)*$E$9-$E$5*$E$10 -> 55500 | C28: =B28/$E$5 -> 555
A30: Insight: profit is dominated by the subscription float and is remarkably insensitive to upgrade frequency, because each redemption still retains a small hardware margin. Volume of members is the lever.

Sheet AT&T Comparison
A1: Side-by-Side — AT&T Upgrade Program vs. TCL Membership
A2: Structural comparison of the two recurring-upgrade models. AT&T terms verified May 2026 (att.com).
A4: Program Mechanics
A5: Dimension | B5: AT&T Next Up Anytime | C5: TCL Tech Solutions Program | D5: Implication for TCL
A6: Monthly fee | B6: $10 / month | C6: $40-$100 / month (tiered) | D6: TCL fee is far higher because the underlying assets ($900-$4,000) dwarf a phone.
A7: What the fee buys | B7: Upgrade eligibility only | C7: Accruing credit toward components | D7: TCL's accruing credit is a genuine differentiator AT&T does not offer.
A8: Credit accrual | B8: None - fee is not applied to balance | C8: Yes - rolls forward, capped | D8: Answers the exact question Damon flagged: 'does my money accumulate?' Yes, with a cap.
A9: Upgrade cadence | B9: Up to 3 per 12 months, anytime after 50% paid | C9: Annual, tier-defined (not anytime) | D9: Annual cadence protects margin and matches slow AV refresh cycles.
A10: Old asset | B10: Must trade in device to waive balance | C10: Customer keeps / TCL may resell | D10: Potential second margin: refurbish-and-resell trade-ins.
A11: Profit engine | B11: Volume + financing + service add-ons | C11: Spread + low redemption freq. + float | D11: Identical logic: large base, infrequent use. Member volume is the lever.
A12: Underlying unit cost | B12: ~$2,000 carrier cost / phone (volume) | C12: $120-$2,800 dealer cost / component | D12: TCL gets the same kind of dealer volume discount AT&T gets on phones.
A13: Lock-in | B13: Installment plan + trade-in dependency | C13: Recurring membership + installed base | D13: Already-installed system creates natural retention; lean into service bundling.
A14: Cancel terms | B14: Cancel anytime; re-enroll within 30 days | C14: Recommend: forfeit unredeemed credit on cancel | D14: Forfeiture-on-cancel discourages churn-after-redemption gaming.
A16: Takeaway: copy AT&T's float-and-volume profit engine, but beat them on the feature their customers wish they had - credit that actually accumulates.
A18: Source: AT&T Next Up Anytime, att.com/plans/next-up-anytime, verified May 2026.
